{"trial_id": "4", "hyperparameters": {"space": [{"class_name": "Choice", "config": {"name": "reg_type", "default": "l1", "conditions": [], "values": ["l1", "l2", "l1_l2", "None"], "ordered": false}}, {"class_name": "Float", "config": {"name": "l1", "default": 0.0001, "conditions": [], "min_value": 0.0001, "max_value": 0.001, "step": null, "sampling": "log"}}, {"class_name": "Float", "config": {"name": "learning_rate", "default": 0.0001, "conditions": [], "min_value": 0.0001, "max_value": 0.1, "step": null, "sampling": "log"}}, {"class_name": "Int", "config": {"name": "batch_size", "default": null, "conditions": [], "min_value": 16, "max_value": 512, "step": 16, "sampling": "linear"}}, {"class_name": "Int", "config": {"name": "epochs", "default": null, "conditions": [], "min_value": 5, "max_value": 25, "step": 5, "sampling": "linear"}}, {"class_name": "Float", "config": {"name": "validation_split", "default": 0.1, "conditions": [], "min_value": 0.1, "max_value": 0.25, "step": null, "sampling": "linear"}}, {"class_name": "Boolean", "config": {"name": "shuffle", "default": false, "conditions": []}}, {"class_name": "Float", "config": {"name": "l2", "default": 0.0001, "conditions": [], "min_value": 0.0001, "max_value": 0.001, "step": null, "sampling": "log"}}], "values": {"reg_type": "None", "l1": 0.0007809133920163749, "learning_rate": 0.03805583437214247, "batch_size": 96, "epochs": 5, "validation_split": 0.22531223803904774, "shuffle": false, "l2": 0.00014244960319939972}}, "metrics": {"metrics": {"accuracy": {"direction": "max", "observations": [{"value": [0.8147569298744202], "step": 2}]}, "loss": {"direction": "min", "observations": [{"value": [0.4950992465019226], "step": 2}]}, "val_accuracy": {"direction": "max", "observations": [{"value": [0.4208611150582631], "step": 2}]}, "val_loss": {"direction": "min", "observations": [{"value": [269.06530507405597], "step": 2}]}}}, "score": 0.4208611150582631, "best_step": 2, "status": "COMPLETED", "message": null}